{
  "variants": {
    "variant=0": { "model": "fd:deepslate_iron_ore" },
    "variant=1": { "model": "fd:deepslate_gold_ore" },
    "variant=2": { "model": "fd:deepslate_copper_ore" },
    "variant=3": { "model": "fd:deepslate_coal_ore" },
    "variant=4": { "model": "fd:deepslate_lapis_ore" },
    "variant=5": { "model": "fd:deepslate_diamond_ore" },
    "variant=6": { "model": "fd:deepslate_emerald_ore" },
    "variant=7": { "model": "fd:deepslate_iron_ore" },
    "variant=8": { "model": "fd:deepslate_iron_ore" },
    "variant=9": { "model": "fd:deepslate_iron_ore" },
    "variant=10": { "model": "fd:deepslate_iron_ore" },
    "variant=11": { "model": "fd:deepslate_iron_ore" },
    "variant=12": { "model": "fd:deepslate_iron_ore" },
    "variant=13": { "model": "fd:deepslate_iron_ore" },
    "variant=14": { "model": "fd:deepslate_iron_ore" },
    "variant=15": { "model": "fd:deepslate_iron_ore" }
  }
}